{
    "服务器": 25382,
    "连接": 20255,
    "尝试": 19853,
    "中": 19847,
    "重生": 16912,
    "妈": 12760,
    "好玩": 12329,
    "逼": 10435,
    "垃圾": 9406,
    "傻": 8811,
    "EA": 7900,
    "玩": 6983,
    "派": 4878,
    "我草": 4077,
    "挂": 3818,
    "答辩": 3605,
    "bug": 3498,
    "死": 3232,
    "真的": 3089,
    "没": 2975,
    "卡卡": 2687,
    "匹配": 2615,
    "队友": 2478,
    "操": 2474,
    "说": 2262,
    "修": 2244,
    "玩家": 2200,
    "ea": 2072,
    "外挂": 2015,
    "b": 1969,
    "机制": 1940,
    "不好玩": 1848,
    "太": 1847,
    "做": 1811,
    "确实": 1645,
    "喜欢": 1634,
    "司马": 1627,
    "烂": 1599,
    "apex": 1566,
    "依托": 1549,
    "排位": 1514,
    "sb": 1476,
    "卡": 1467,
    "真": 1406,
    "封": 1381,
    "nm": 1373,
    "狗": 1366,
    "妈妈": 1325,
    "APEX": 1323,
    "草拟": 1320,
    "皮肤": 1293,
    "修修": 1280,
    "赛季": 1279,
    "小时": 1264,
    "牛子": 1250,
    "天天": 1216,
    "人机": 1196,
    "草": 1191,
    "想": 1164,
    "一坨": 1151,
    "体验": 1125,
    "出": 1113,
    "不错": 1079,
    "屎": 1075,
    "传家宝": 1074,
    "玩别": 983,
    "朋友": 918,
    "买": 918,
    "尼玛": 903,
    "钱": 855,
    "大逃杀": 855,
    "全是": 852,
    "一点": 838,
    "草泥马": 834,
    "反作弊": 828,
    "炸": 826,
    "好好": 824,
    "号": 810,
    "里": 809,
    "东西": 801,
    "吃": 797,
    "猎杀": 784,
    "马": 783,
    "新手": 770,
    "更新": 755,
    "想要": 744,
    "狗屎": 743,
    "不修": 736,
    "头像": 735,
    "推荐": 732,
    "奖励": 728,
    "good": 727,
    "一把": 727,
    "少": 722,
    "掉": 721,
    "煞笔": 721,
    "请": 718,
    "感觉": 712,
    "评价": 707,
    "差": 684
}